odoo/addons/website_snippet_dynamic_link/README.rst
odoo/addons/website_snippet_dynamic_link/__init__.py
odoo/addons/website_snippet_dynamic_link/__manifest__.py
odoo/addons/website_snippet_dynamic_link/menuitems.xml
odoo/addons/website_snippet_dynamic_link/i18n/es.po
odoo/addons/website_snippet_dynamic_link/i18n/it.po
odoo/addons/website_snippet_dynamic_link/i18n/website_snippet_dynamic_link.pot
odoo/addons/website_snippet_dynamic_link/models/__init__.py
odoo/addons/website_snippet_dynamic_link/models/website_dynamic_link.py
odoo/addons/website_snippet_dynamic_link/readme/CONFIGURE.rst
odoo/addons/website_snippet_dynamic_link/readme/CONTRIBUTORS.rst
odoo/addons/website_snippet_dynamic_link/readme/DESCRIPTION.rst
odoo/addons/website_snippet_dynamic_link/readme/USAGE.rst
odoo/addons/website_snippet_dynamic_link/security/ir.model.access.csv
odoo/addons/website_snippet_dynamic_link/static/description/icon.png
odoo/addons/website_snippet_dynamic_link/static/description/index.html
odoo/addons/website_snippet_dynamic_link/static/src/img/snippets_thumbs/s_dynamic_link.svg
odoo/addons/website_snippet_dynamic_link/static/src/snippets/s_dynamic_link/000.js
odoo/addons/website_snippet_dynamic_link/static/src/snippets/s_dynamic_link/000.scss
odoo/addons/website_snippet_dynamic_link/static/src/snippets/s_dynamic_link/000.xml
odoo/addons/website_snippet_dynamic_link/views/website_dynamic_link_view.xml
odoo/addons/website_snippet_dynamic_link/views/snippets/s_dynamic_link.xml
odoo/addons/website_snippet_dynamic_link/views/snippets/snippets.xml
odoo_addon_website_snippet_dynamic_link-15.0.1.0.0.7.dist-info/METADATA
odoo_addon_website_snippet_dynamic_link-15.0.1.0.0.7.dist-info/WHEEL
odoo_addon_website_snippet_dynamic_link-15.0.1.0.0.7.dist-info/top_level.txt
odoo_addon_website_snippet_dynamic_link-15.0.1.0.0.7.dist-info/RECORD
